lmprobe/__init__.py
lmprobe/activation_baseline.py
lmprobe/baseline.py
lmprobe/battery.py
lmprobe/cache.py
lmprobe/classifiers.py
lmprobe/extraction.py
lmprobe/plotting.py
lmprobe/pooling.py
lmprobe/probe.py
lmprobe/scaling.py
lmprobe/unified_cache.py
lmprobe-0.4.2.dist-info/METADATA
lmprobe-0.4.2.dist-info/WHEEL
lmprobe-0.4.2.dist-info/licenses/LICENSE
lmprobe-0.4.2.dist-info/RECORD
