Metadata-Version: 2.4
Name: lmprobe
Version: 0.4.2
Summary: Train linear probes on language model activations for AI safety monitoring
Project-URL: Homepage, https://github.com/toast/lmprobe
Project-URL: Documentation, https://github.com/toast/lmprobe#readme
Project-URL: Repository, https://github.com/toast/lmprobe
Author: Toast
License-Expression: MIT
License-File: LICENSE
Keywords: ai-safety,interpretability,language-models,machine-learning,nlp,probing
Classifier: Development Status :: 3 - Alpha
Classifier: Intended Audience :: Science/Research
Classifier: License :: OSI Approved :: MIT License
Classifier: Programming Language :: Python :: 3
Classifier: Programming Language :: Python :: 3.10
Classifier: Programming Language :: Python :: 3.11
Classifier: Programming Language :: Python :: 3.12
Classifier: Topic :: Scientific/Engineering :: Artificial Intelligence
Requires-Python: >=3.10
Requires-Dist: nnsight>=0.3
Requires-Dist: numpy>=1.20
Requires-Dist: scikit-learn>=1.0
Requires-Dist: torch>=2.0
Requires-Dist: tqdm>=4.0
Requires-Dist: transformers>=4.30
Provides-Extra: auto
Requires-Dist: skglm>=0.3; extra == 'auto'
Provides-Extra: dev
Requires-Dist: black>=23.0; extra == 'dev'
Requires-Dist: pytest-cov>=4.0; extra == 'dev'
Requires-Dist: pytest>=7.0; extra == 'dev'
Requires-Dist: ruff>=0.1; extra == 'dev'
Provides-Extra: embeddings
Requires-Dist: sentence-transformers>=2.0; extra == 'embeddings'
Provides-Extra: plot
Requires-Dist: matplotlib>=3.5; extra == 'plot'
Requires-Dist: seaborn>=0.12; extra == 'plot'
